{
  "kind": "collectionType",
  "collectionName": "shoes",
  "info": {
    "singularName": "shoe",
    "pluralName": "shoes",
    "displayName": "Shoe",
    "description": ""
  },
  "options": {
    "draftAndPublish": true
  },
  "pluginOptions": {},
  "attributes": {
    "image": {
      "type": "media",
      "multiple": false,
      "required": false,
      "allowedTypes": [
        "images",
        "files",
        "videos",
        "audios"
      ]
    },
    "name": {
      "type": "string",
      "required": true,
      "unique": false
    },
    "price": {
      "type": "decimal",
      "required": true
    },
    "discount": {
      "type": "decimal"
    }
  }
}
